envargs/__init__.py
envargs/errors.py
envargs/helpers.py
envargs/models.py
envargs/parser.py
envargs-0.2.1.dist-info/DESCRIPTION.rst
envargs-0.2.1.dist-info/METADATA
envargs-0.2.1.dist-info/RECORD
envargs-0.2.1.dist-info/WHEEL
envargs-0.2.1.dist-info/metadata.json
envargs-0.2.1.dist-info/top_level.txt
