Metadata-Version: 2.0
Name: envargs
Version: 0.2.1
Summary: Parsing and validation of environment variables
Home-page: https://github.com/cknv/envargs
Author: Esben Sonne
Author-email: esbensonne+code@gmail.com
License: MIT
Platform: UNKNOWN
Classifier: Development Status :: 4 - Beta
Classifier: Intended Audience :: Developers
Classifier: License :: OSI Approved :: MIT License
Classifier: Programming Language :: Python :: 3.3
Classifier: Programming Language :: Python :: 3.4
Classifier: Programming Language :: Python :: 3.5
Classifier: Programming Language :: Python :: 3.6
